pygments_tldr/__init__.py
pygments_tldr/__main__.py
pygments_tldr/cmdline.py
pygments_tldr/console.py
pygments_tldr/filter.py
pygments_tldr/formatter.py
pygments_tldr/lexer.py
pygments_tldr/modeline.py
pygments_tldr/plugin.py
pygments_tldr/regexopt.py
pygments_tldr/scanner.py
pygments_tldr/sphinxext.py
pygments_tldr/style.py
pygments_tldr/token.py
pygments_tldr/unistring.py
pygments_tldr/util.py
pygments_tldr/filters/__init__.py
pygments_tldr/formatters/__init__.py
pygments_tldr/formatters/_mapping.py
pygments_tldr/formatters/bbcode.py
pygments_tldr/formatters/groff.py
pygments_tldr/formatters/html.py
pygments_tldr/formatters/img.py
pygments_tldr/formatters/irc.py
pygments_tldr/formatters/latex.py
pygments_tldr/formatters/other.py
pygments_tldr/formatters/pangomarkup.py
pygments_tldr/formatters/rtf.py
pygments_tldr/formatters/svg.py
pygments_tldr/formatters/terminal.py
pygments_tldr/formatters/terminal256.py
pygments_tldr/formatters/tldr.py
pygments_tldr/lexers/__init__.py
pygments_tldr/lexers/_ada_builtins.py
pygments_tldr/lexers/_asy_builtins.py
pygments_tldr/lexers/_cl_builtins.py
pygments_tldr/lexers/_cocoa_builtins.py
pygments_tldr/lexers/_csound_builtins.py
pygments_tldr/lexers/_css_builtins.py
pygments_tldr/lexers/_googlesql_builtins.py
pygments_tldr/lexers/_julia_builtins.py
pygments_tldr/lexers/_lasso_builtins.py
pygments_tldr/lexers/_lilypond_builtins.py
pygments_tldr/lexers/_lua_builtins.py
pygments_tldr/lexers/_luau_builtins.py
pygments_tldr/lexers/_mapping.py
pygments_tldr/lexers/_mql_builtins.py
pygments_tldr/lexers/_mysql_builtins.py
pygments_tldr/lexers/_openedge_builtins.py
pygments_tldr/lexers/_php_builtins.py
pygments_tldr/lexers/_postgres_builtins.py
pygments_tldr/lexers/_qlik_builtins.py
pygments_tldr/lexers/_scheme_builtins.py
pygments_tldr/lexers/_scilab_builtins.py
pygments_tldr/lexers/_sourcemod_builtins.py
pygments_tldr/lexers/_sql_builtins.py
pygments_tldr/lexers/_stan_builtins.py
pygments_tldr/lexers/_stata_builtins.py
pygments_tldr-2.19.3.0.dist-info/METADATA
pygments_tldr-2.19.3.0.dist-info/WHEEL
pygments_tldr-2.19.3.0.dist-info/entry_points.txt
pygments_tldr-2.19.3.0.dist-info/licenses/AUTHORS
pygments_tldr-2.19.3.0.dist-info/licenses/LICENSE
pygments_tldr-2.19.3.0.dist-info/RECORD
