Metadata-Version: 2.4
Name: Pygments-tldr
Version: 2.19.3.0
Summary: Pygments-tldr is a fork of pygments with a formatter to extract function signatures
Project-URL: Homepage, https://github.com/csimoes1/pygments-tldr
Project-URL: Documentation, https://github.com/csimoes1/pygments-tldr
Project-URL: Source, https://github.com/csimoes1/pygments-tldr
Project-URL: Bug Tracker, https://github.com/csimoes1/pygments-tldr
Project-URL: Changelog, https://github.com/csimoes1/pygments-tldr/blob/master/CHANGES
Author-email: Chris Simoes <csimoes1@yahoo.com>
Maintainer-email: Chris Simoes <csimoes1@yahoo.com>
License: BSD-2-Clause
License-File: AUTHORS
License-File: LICENSE
Keywords: syntax highlighting
Classifier: Development Status :: 6 - Mature
Classifier: Intended Audience :: Developers
Classifier: Intended Audience :: End Users/Desktop
Classifier: Intended Audience :: System Administrators
Classifier: License :: OSI Approved :: BSD License
Classifier: Operating System :: OS Independent
Classifier: Programming Language :: Python
Classifier: Programming Language :: Python :: 3
Classifier: Programming Language :: Python :: 3.8
Classifier: Programming Language :: Python :: 3.9
Classifier: Programming Language :: Python :: 3.10
Classifier: Programming Language :: Python :: 3.11
Classifier: Programming Language :: Python :: 3.12
Classifier: Programming Language :: Python :: 3.13
Classifier: Programming Language :: Python :: Implementation :: CPython
Classifier: Programming Language :: Python :: Implementation :: PyPy
Classifier: Topic :: Text Processing :: Filters
Classifier: Topic :: Utilities
Requires-Python: >=3.8
Provides-Extra: plugins
Provides-Extra: windows-terminal
Requires-Dist: colorama>=0.4.6; extra == 'windows-terminal'
